[
  {
    "timestamp": "2025-10-05T18:31:16.999Z",
    "stats": {
      "totalSize": 1889550,
      "totalGzipSize": 602528,
      "chunkCount": 23,
      "largestChunk": 645939
    }
  },
  {
    "timestamp": "2025-10-05T18:36:56.796Z",
    "stats": {
      "totalSize": 1889550,
      "totalGzipSize": 602510,
      "chunkCount": 23,
      "largestChunk": 645939
    }
  },
  {
    "timestamp": "2025-10-14T11:41:43.865Z",
    "stats": {
      "totalSize": 1950496,
      "totalGzipSize": 620495,
      "chunkCount": 24,
      "largestChunk": 645516
    }
  },
  {
    "timestamp": "2025-10-14T13:19:27.791Z",
    "stats": {
      "totalSize": 1946262,
      "totalGzipSize": 618278,
      "chunkCount": 22,
      "largestChunk": 678031
    }
  },
  {
    "timestamp": "2025-10-14T13:33:35.214Z",
    "stats": {
      "totalSize": 1946262,
      "totalGzipSize": 618304,
      "chunkCount": 22,
      "largestChunk": 678031
    }
  },
  {
    "timestamp": "2025-10-14T13:35:38.184Z",
    "stats": {
      "totalSize": 1946262,
      "totalGzipSize": 618304,
      "chunkCount": 22,
      "largestChunk": 678031
    }
  },
  {
    "timestamp": "2025-11-21T18:17:40.598Z",
    "stats": {
      "totalSize": 11288265,
      "totalGzipSize": 2246897,
      "chunkCount": 21,
      "largestChunk": 9933982
    }
  },
  {
    "timestamp": "2025-11-21T18:47:04.196Z",
    "stats": {
      "totalSize": 11288265,
      "totalGzipSize": 2246901,
      "chunkCount": 21,
      "largestChunk": 9933982
    }
  },
  {
    "timestamp": "2025-11-21T19:06:39.641Z",
    "stats": {
      "totalSize": 11288265,
      "totalGzipSize": 2246876,
      "chunkCount": 21,
      "largestChunk": 9933982
    }
  },
  {
    "timestamp": "2025-11-21T19:26:25.588Z",
    "stats": {
      "totalSize": 11288267,
      "totalGzipSize": 2246883,
      "chunkCount": 21,
      "largestChunk": 9933984
    }
  },
  {
    "timestamp": "2025-11-21T19:32:51.483Z",
    "stats": {
      "totalSize": 11043001,
      "totalGzipSize": 2178515,
      "chunkCount": 36,
      "largestChunk": 9750573
    }
  },
  {
    "timestamp": "2026-01-25T19:18:18.324Z",
    "summary": {
      "totalSize": 13568477,
      "totalGzip": 3075931,
      "totalBrotli": 2530652,
      "jsCount": 486,
      "cssCount": 29
    }
  },
  {
    "timestamp": "2026-01-25T19:21:26.123Z",
    "summary": {
      "totalSize": 13568477,
      "totalGzip": 3075931,
      "totalBrotli": 2530652,
      "jsCount": 486,
      "cssCount": 29
    }
  },
  {
    "timestamp": "2026-01-25T19:22:10.742Z",
    "summary": {
      "totalSize": 13568477,
      "totalGzip": 3075931,
      "totalBrotli": 2530652,
      "jsCount": 486,
      "cssCount": 29
    }
  },
  {
    "timestamp": "2026-01-25T19:23:23.831Z",
    "summary": {
      "totalSize": 13568477,
      "totalGzip": 3075931,
      "totalBrotli": 2530652,
      "jsCount": 486,
      "cssCount": 29
    }
  },
  {
    "timestamp": "2026-01-25T19:27:45.152Z",
    "summary": {
      "totalSize": 13568477,
      "totalGzip": 3075931,
      "totalBrotli": 2530652,
      "jsCount": 486,
      "cssCount": 29
    }
  },
  {
    "timestamp": "2026-01-25T19:28:08.886Z",
    "summary": {
      "totalSize": 13568477,
      "totalGzip": 3075931,
      "totalBrotli": 2530652,
      "jsCount": 486,
      "cssCount": 29
    }
  }
]